tomtom_apis/__init__.py
tomtom_apis/api.py
tomtom_apis/const.py
tomtom_apis/exceptions.py
tomtom_apis/models.py
tomtom_apis/py.typed
tomtom_apis/utils.py
tomtom_apis/automotive/__init__.py
tomtom_apis/automotive/autostream.py
tomtom_apis/automotive/fuel_prices.py
tomtom_apis/automotive/models.py
tomtom_apis/automotive/parking_availability.py
tomtom_apis/maps/__init__.py
tomtom_apis/maps/map_display.py
tomtom_apis/maps/models.py
tomtom_apis/places/__init__.py
tomtom_apis/places/batch_search.py
tomtom_apis/places/ev_search.py
tomtom_apis/places/geocoding.py
tomtom_apis/places/models.py
tomtom_apis/places/premium_geocoding.py
tomtom_apis/places/reverse_geocoding.py
tomtom_apis/places/search.py
tomtom_apis/routing/__init__.py
tomtom_apis/routing/long_distance_ev_routing.py
tomtom_apis/routing/matrix_routing_v2.py
tomtom_apis/routing/models.py
tomtom_apis/routing/routing.py
tomtom_apis/routing/waypoint_optimization.py
tomtom_apis/tracking_logistics/__init__.py
tomtom_apis/tracking_logistics/geofencing.py
tomtom_apis/tracking_logistics/location_history.py
tomtom_apis/tracking_logistics/models.py
tomtom_apis/tracking_logistics/notifications.py
tomtom_apis/tracking_logistics/snap_to_roads.py
tomtom_apis/traffic/__init__.py
tomtom_apis/traffic/intermediate_traffic.py
tomtom_apis/traffic/junction_analytics.py
tomtom_apis/traffic/models.py
tomtom_apis/traffic/od_analytics.py
tomtom_apis/traffic/route_monitoring.py
tomtom_apis/traffic/traffic.py
tomtom_apis/traffic/traffic_stats.py
tomtom_apis-0.1.0.dist-info/METADATA
tomtom_apis-0.1.0.dist-info/WHEEL
tomtom_apis-0.1.0.dist-info/licenses/LICENSE
tomtom_apis-0.1.0.dist-info/RECORD
