Metadata-Version: 2.4
Name: tomtom-apis
Version: 0.1.0
Summary: Asynchronous Python client for the TomTom APIs
Project-URL: Documentation, https://github.com/golles/tomtom-apis-python
Project-URL: Homepage, https://github.com/golles/tomtom-apis-python
Project-URL: Repository, https://github.com/golles/tomtom-apis-python
Project-URL: Issues, https://github.com/golles/tomtom-apis-python/issues
Author-email: Sander Gols <developer@golles.nl>
License-Expression: MIT
License-File: LICENSE
Classifier: Development Status :: 3 - Alpha
Classifier: Framework :: AsyncIO
Classifier: Intended Audience :: Developers
Classifier: Intended Audience :: Science/Research
Classifier: License :: OSI Approved :: MIT License
Classifier: Natural Language :: English
Classifier: Operating System :: OS Independent
Classifier: Programming Language :: Python :: 3
Classifier: Programming Language :: Python :: 3.13
Classifier: Topic :: Software Development :: Libraries :: Python Modules
Requires-Python: <3.14,>=3.13
Requires-Dist: aiohttp>=3.12.0
Requires-Dist: geojson>=3.2.0
Requires-Dist: mashumaro>=3.16
Requires-Dist: orjson>=3.10.0
